simless/__init__.py
simless/configurations.py
simless/descriptors.py
simless/ned_component.py
simless/parameters.py
simless/runner.py
simless/runs_frame.py
simless/sections.py
simless/sim_dir.py
simless/simulation.py
simless/topology.py
simless/workloads.py
simless-0.0.17.dist-info/licenses/LICENSE
simless-0.0.17.dist-info/METADATA
simless-0.0.17.dist-info/WHEEL
simless-0.0.17.dist-info/top_level.txt
simless-0.0.17.dist-info/RECORD
